examplelspserver/__init__.py
examplelspserver/__main__.py
examplelspserver/cst/__init__.py
examplelspserver/cst/diagnostic_listener.py
examplelspserver/cst/symbol_table_visitor.py
examplelspserver/cst/verbose_listener.py
examplelspserver/filewriter/__init__.py
examplelspserver/filewriter/jinja-templates/test_template.txt
examplelspserver/gen/java/TestExprCore/TestExprCore.interp
examplelspserver/gen/java/TestExprCore/TestExprCore.tokens
examplelspserver/gen/java/TestExprCore/TestExprCoreBaseListener.java
examplelspserver/gen/java/TestExprCore/TestExprCoreBaseVisitor.java
examplelspserver/gen/java/TestExprCore/TestExprCoreLexer.interp
examplelspserver/gen/java/TestExprCore/TestExprCoreLexer.java
examplelspserver/gen/java/TestExprCore/TestExprCoreLexer.tokens
examplelspserver/gen/java/TestExprCore/TestExprCoreListener.java
examplelspserver/gen/java/TestExprCore/TestExprCoreParser.java
examplelspserver/gen/java/TestExprCore/TestExprCoreVisitor.java
examplelspserver/gen/java/exampleDsl/exampleDsl.interp
examplelspserver/gen/java/exampleDsl/exampleDsl.tokens
examplelspserver/gen/java/exampleDsl/exampleDslBaseListener.java
examplelspserver/gen/java/exampleDsl/exampleDslBaseVisitor.java
examplelspserver/gen/java/exampleDsl/exampleDslLexer.interp
examplelspserver/gen/java/exampleDsl/exampleDslLexer.java
examplelspserver/gen/java/exampleDsl/exampleDslLexer.tokens
examplelspserver/gen/java/exampleDsl/exampleDslListener.java
examplelspserver/gen/java/exampleDsl/exampleDslParser.java
examplelspserver/gen/java/exampleDsl/exampleDslVisitor.java
examplelspserver/gen/python/TestExprCore/TestExprCore.interp
examplelspserver/gen/python/TestExprCore/TestExprCore.tokens
examplelspserver/gen/python/TestExprCore/TestExprCoreLexer.interp
examplelspserver/gen/python/TestExprCore/TestExprCoreLexer.py
examplelspserver/gen/python/TestExprCore/TestExprCoreLexer.tokens
examplelspserver/gen/python/TestExprCore/TestExprCoreListener.py
examplelspserver-0.0.3.2.dist-info/LICENSE.txt
examplelspserver-0.0.3.2.dist-info/METADATA
examplelspserver-0.0.3.2.dist-info/WHEEL
examplelspserver-0.0.3.2.dist-info/RECORD
