Metadata-Version: 2.1
Name: examplelspserver
Version: 0.0.3.2
Summary: python packaging tutorial
License: Apache License, Version 2.0
Author: sgu
Author-email: stu126367@mail.uni-kiel.de
Requires-Python: >=3.10,<4.0
Classifier: License :: Other/Proprietary License
Classifier: Programming Language :: Python :: 3
Classifier: Programming Language :: Python :: 3.10
Classifier: Programming Language :: Python :: 3.11
Classifier: Programming Language :: Python :: 3.12
